wecoded/__init__.py
wecoded/__main__.py
wecoded-0.2.0.dist-info/LICENSE
wecoded-0.2.0.dist-info/METADATA
wecoded-0.2.0.dist-info/WHEEL
wecoded-0.2.0.dist-info/entry_points.txt
wecoded-0.2.0.dist-info/top_level.txt
wecoded-0.2.0.dist-info/RECORD
