Metadata-Version: 2.1
Name: wecoded
Version: 0.2.0
Summary: A tool for counting contributed lines by authors on multiple git repositories
Home-page: https://github.com/jctophefabre/wecoded
Author: Jean-Christophe Fabre
Author-email: jean-christophe.fabre@inrae.fr
License: MIT
Platform: UNKNOWN
Requires-Python: ~=3.6
License-File: LICENSE
